odoo/addons/product_category_type/README.rst
odoo/addons/product_category_type/__init__.py
odoo/addons/product_category_type/__manifest__.py
odoo/addons/product_category_type/demo/product_category.xml
odoo/addons/product_category_type/i18n/product_category_type.pot
odoo/addons/product_category_type/models/__init__.py
odoo/addons/product_category_type/models/product_category.py
odoo/addons/product_category_type/models/product_template.py
odoo/addons/product_category_type/readme/CONTRIBUTORS.rst
odoo/addons/product_category_type/readme/DESCRIPTION.rst
odoo/addons/product_category_type/static/description/icon.png
odoo/addons/product_category_type/static/description/index.html
odoo/addons/product_category_type/static/description/product_category_tree.png
odoo/addons/product_category_type/static/description/product_template_form.png
odoo/addons/product_category_type/views/product_category.xml
odoo12_addon_product_category_type-12.0.1.0.1.dist-info/METADATA
odoo12_addon_product_category_type-12.0.1.0.1.dist-info/WHEEL
odoo12_addon_product_category_type-12.0.1.0.1.dist-info/top_level.txt
odoo12_addon_product_category_type-12.0.1.0.1.dist-info/RECORD
